adafruit_mprls.py
adafruit_circuitpython_mprls-1.2.24.dist-info/licenses/LICENSE
adafruit_circuitpython_mprls-1.2.24.dist-info/METADATA
adafruit_circuitpython_mprls-1.2.24.dist-info/WHEEL
adafruit_circuitpython_mprls-1.2.24.dist-info/top_level.txt
adafruit_circuitpython_mprls-1.2.24.dist-info/RECORD
